ps_cli/__init__.py
ps_cli/__version__.py
ps_cli/controllers/__init__.py
ps_cli/controllers/access_levels.py
ps_cli/controllers/access_policies.py
ps_cli/controllers/address_groups.py
ps_cli/controllers/aliases.py
ps_cli/controllers/api_registrations.py
ps_cli/controllers/applications.py
ps_cli/controllers/assets.py
ps_cli/controllers/attribute_types.py
ps_cli/controllers/attributes.py
ps_cli/controllers/credentials.py
ps_cli/controllers/databases.py
ps_cli/controllers/dss_key_policies.py
ps_cli/controllers/entitlements.py
ps_cli/controllers/entity_types.py
ps_cli/controllers/epm_policies.py
ps_cli/controllers/folders.py
ps_cli/controllers/functional_accounts.py
ps_cli/controllers/isa_requests.py
ps_cli/controllers/keystrokes.py
ps_cli/controllers/managed_accounts.py
ps_cli/controllers/managed_systems.py
ps_cli/controllers/operating_systems.py
ps_cli/controllers/oracle_internet_directories.py
ps_cli/controllers/organizations.py
ps_cli/controllers/password_rules.py
ps_cli/controllers/permissions.py
ps_cli/controllers/platforms.py
ps_cli/controllers/propagation_action_types.py
ps_cli/controllers/propagation_actions.py
ps_cli/controllers/quick_rules.py
ps_cli/controllers/raw.py
ps_cli/controllers/replay.py
ps_cli/controllers/requests.py
ps_cli/controllers/roles.py
ps_cli/controllers/safes.py
ps_cli/controllers/secrets.py
ps_cli/controllers/session_locking.py
ps_cli/controllers/session_termination.py
ps_cli/controllers/sessions.py
ps_cli/controllers/settings.py
ps_cli/controllers/short_commands.py
ps_cli/controllers/smart_rules.py
ps_cli/controllers/subscriptions_delivery.py
ps_cli/controllers/ticket_systems.py
ps_cli/controllers/user_group_roles.py
ps_cli/controllers/usergroups.py
ps_cli/controllers/users.py
ps_cli/controllers/workgroups.py
ps_cli/core/__init__.py
ps_cli/core/app.py
ps_cli/core/constants/__init__.py
ps_cli/core/constants/delimiters.py
ps_cli/core/constants/formats.py
ps_cli/core/controllers.py
ps_cli/core/decorators.py
ps_cli/core/display.py
beyondtrust_bips_cli-0.12.1.dist-info/METADATA
beyondtrust_bips_cli-0.12.1.dist-info/WHEEL
beyondtrust_bips_cli-0.12.1.dist-info/entry_points.txt
beyondtrust_bips_cli-0.12.1.dist-info/RECORD
