Metadata-Version: 2.4
Name: beyondtrust-bips-cli
Version: 0.12.1
Summary: PS CLI is a CLI tool designed to allow the execution of BeyondInsight and Password Safe API calls
Author: BeyondTrust Corporation
Author-email: support@beyondtrust.com
Requires-Python: >=3.11
Classifier: Programming Language :: Python :: 3
Classifier: Programming Language :: Python :: 3.11
Classifier: Programming Language :: Python :: 3.12
Classifier: Programming Language :: Python :: 3.13
Classifier: Programming Language :: Python :: 3.14
Requires-Dist: beyondtrust-bips-library (>=2.0.0,<3.0.0)
Requires-Dist: chardet (>=5.2.0,<6.0.0)
Requires-Dist: requests[use-chardet-on-py3] (>=2.32.3,<3.0.0)
Requires-Dist: retry-requests (>=2.0.0,<3.0.0)
